tinyllama/__init__.py
tinyllama/activations/__init__.py
tinyllama/activations/swiglu.py
tinyllama/diagnosis/__init__.py
tinyllama/diagnosis/diagnosis.py
tinyllama/diagnosis/gdratio_diagnose.py
tinyllama/diagnosis/gradient_diagnose.py
tinyllama/diagnosis/lr_diagnose.py
tinyllama/diagnosis/swiglu_diagnose.py
tinyllama/encoding/__init__.py
tinyllama/encoding/roPE.py
tinyllama/generate/__init__.py
tinyllama/generate/generate.py
tinyllama/gptuner/__init__.py
tinyllama/gptuner/gptuner.py
tinyllama/gptuner/gptuner.stan
tinyllama/models/__init__.py
tinyllama/models/llama.py
tinyllama/normalization/__init__.py
tinyllama/normalization/rms.py
tinyllama/readers/__init__.py
tinyllama/readers/readers.py
tinyllama/tokenizers/__init__.py
tinyllama/tokenizers/tokenizers.py
tinyllama/training/__init__.py
tinyllama/training/training.py
tinyllama-0.0.291.dist-info/METADATA
tinyllama-0.0.291.dist-info/WHEEL
tinyllama-0.0.291.dist-info/licenses/LICENSE
tinyllama-0.0.291.dist-info/RECORD
