Metadata-Version: 2.1
Name: tinyllama
Version: 0.0.291
Summary: Model classes and pre-training utilities for a tiny version of Llama in PyTorch.
Project-URL: repository, https://github.com/miftahmoha/tinyllama
Author-email: Achraf Miftah <mbns.miftah.achraf@gmail.com>
License:                                 Apache License
License-File: LICENSE
Keywords: deep-learning,llama,llm,tinyllama
Classifier: Development Status :: 3 - Alpha
Classifier: Intended Audience :: Developers
Classifier: Intended Audience :: Information Technology
Classifier: Intended Audience :: Science/Research
Classifier: License :: OSI Approved :: Apache Software License
Classifier: Natural Language :: English
Classifier: Programming Language :: Python :: 3
Classifier: Topic :: Scientific/Engineering :: Artificial Intelligence
Classifier: Topic :: Scientific/Engineering :: Information Analysis
Classifier: Topic :: Scientific/Engineering :: Mathematics
Requires-Python: ~=3.9
Requires-Dist: matplotlib
Requires-Dist: numpy
Requires-Dist: pandas
Requires-Dist: pypdf2
Requires-Dist: pystan
Requires-Dist: torch
Requires-Dist: tqdm
Provides-Extra: dev
Requires-Dist: pip-tools; extra == 'dev'
Requires-Dist: pytest; extra == 'dev'
